Metadata-Version: 2.1
Name: menutools
Version: 1.0.5
Summary: Create command line menu
Home-page: https://github.com/J-Yaghoubi/menutools
Author: Seyed Jafar Yaghoubi
Author-email: algo3xp3rt@gmail.com
License: MIT
Requires-Python: >=3.8
License-File: LICENCE
